shaheenai/__init__.py
shaheenai/agent.py
shaheenai/cli.py
shaheenai/config.py
shaheenai/mcp.py
shaheenai/version.py
shaheenai/llm_providers/__init__.py
shaheenai/llm_providers/base.py
shaheenai/llm_providers/cohere.py
shaheenai/llm_providers/factory.py
shaheenai/llm_providers/google.py
shaheenai/llm_providers/openai.py
shaheenai/llm_providers/openrouter.py
shaheenai/research/__init__.py
shaheenai/research/bibliography.py
shaheenai/research/planner.py
shaheenai/research/project.py
shaheenai/research/templates.py
shaheenai/tools/__init__.py
shaheenai/tools/base.py
shaheenai/ui/__init__.py
shaheenai/ui/chainlit_ui.py
shaheenai/ui/streamlit_ui.py
shaheenai-0.2.1.dist-info/licenses/LICENSE
shaheenai-0.2.1.dist-info/METADATA
shaheenai-0.2.1.dist-info/WHEEL
shaheenai-0.2.1.dist-info/entry_points.txt
shaheenai-0.2.1.dist-info/top_level.txt
shaheenai-0.2.1.dist-info/RECORD
