Metadata-Version: 2.4
Name: shaheenai
Version: 0.2.1
Summary: A flexible, multi-LLM, agent-oriented Python library with self-reflection capabilities
Author: Hamza - AI Engineer, Python Developer, Machine Learning, Agentic AI, Data Science, Node, Express, Typescript, NextJS
License-Expression: MIT
Project-URL: Homepage, https://github.com/hamza/shaheenai
Project-URL: Documentation, https://shaheenai.readthedocs.io
Project-URL: Repository, https://github.com/hamza/shaheenai
Project-URL: Bug Tracker, https://github.com/hamza/shaheenai/issues
Keywords: ai,llm,agents,automation,openai,groq,gemini
Classifier: Development Status :: 4 - Beta
Classifier: Intended Audience :: Developers
Classifier: Programming Language :: Python :: 3
Classifier: Programming Language :: Python :: 3.10
Classifier: Programming Language :: Python :: 3.11
Classifier: Programming Language :: Python :: 3.12
Classifier: Topic :: Scientific/Engineering :: Artificial Intelligence
Classifier: Topic :: Software Development :: Libraries :: Python Modules
Requires-Python: >=3.10
License-File: LICENSE
Requires-Dist: pydantic>=2.0.0
Requires-Dist: pyyaml>=6.0
Requires-Dist: httpx>=0.25.0
Requires-Dist: litellm>=1.0.0
Requires-Dist: fastapi>=0.100.0
Requires-Dist: uvicorn>=0.23.0
Requires-Dist: click>=8.0.0
Requires-Dist: typing-extensions>=4.0.0
Provides-Extra: openai
Requires-Dist: openai>=1.0.0; extra == "openai"
Provides-Extra: anthropic
Requires-Dist: anthropic>=0.7.0; extra == "anthropic"
Provides-Extra: cohere
Requires-Dist: cohere>=4.0.0; extra == "cohere"
Provides-Extra: groq
Requires-Dist: groq>=0.4.0; extra == "groq"
Provides-Extra: ollama
Requires-Dist: ollama>=0.1.0; extra == "ollama"
Provides-Extra: streamlit
Requires-Dist: streamlit>=1.28.0; extra == "streamlit"
Provides-Extra: chainlit
Requires-Dist: chainlit>=1.0.0; extra == "chainlit"
Provides-Extra: ui
Requires-Dist: streamlit>=1.28.0; extra == "ui"
Requires-Dist: chainlit>=1.0.0; extra == "ui"
Provides-Extra: all
Requires-Dist: openai>=1.0.0; extra == "all"
Requires-Dist: anthropic>=0.7.0; extra == "all"
Requires-Dist: cohere>=4.0.0; extra == "all"
Requires-Dist: groq>=0.4.0; extra == "all"
Requires-Dist: ollama>=0.1.0; extra == "all"
Requires-Dist: streamlit>=1.28.0; extra == "all"
Requires-Dist: chainlit>=1.0.0; extra == "all"
Dynamic: license-file
